teapy-0.9.0.dist-info/METADATA
teapy-0.9.0.dist-info/WHEEL
teapy-0.9.0.dist-info/licenses/LICENSE
teapy/__init__.py
teapy/array_func.py
teapy/expr.py
teapy/mod_func.py
teapy/py_datadict.py
teapy/regression.py
teapy/selector.py
teapy/tears.pyd
teapy/testing.py
teapy/tests/test_array_func.py
teapy/tests/test_common.py
teapy/tests/test_context.py
teapy/tests/test_datadict.py
teapy/tests/test_equity.py
teapy/tests/test_expr.py
teapy/tests/test_memory.py
teapy/tests/test_time.py
teapy/tests/window/test_compare.py
teapy/tests/window/test_corr.py
teapy/tests/window/test_feature.py
teapy/tests/window/test_norm.py
teapy/tests/window/test_reg.py
teapy/window_func.py
teapy/wrapper.py
teapy-0.9.0.dist-info/RECORD
