Metadata-Version: 2.4
Name: teapy
Version: 0.9.0
Classifier: Programming Language :: Rust
Classifier: Programming Language :: Python :: Implementation :: CPython
Classifier: Programming Language :: Python :: Implementation :: PyPy
Classifier: License :: OSI Approved :: MIT License
Requires-Dist: numpy>=1.16.0
License-File: LICENSE
Summary: A blazingly fast datadict library
Author-email: Teamon <teamon9161@163.com>
Requires-Python: >=3.8
